graphet/__init__.py
graphet/dashboard.py
graphet/data.py
graphet/plugin.py
graphet/test_tristanv2.py
graphet/plugins/__init__.py
graphet/plugins/tristanv2.py
graphet/tests/data/fakedata.py
graphet/tests/data/tristanv2/input.cfg
graphet/tests/data/tristanv2/flds/flds.tot.00000
graphet/tests/data/tristanv2/flds/flds.tot.00001
graphet/tests/data/tristanv2/flds/flds.tot.00002
graphet/tests/data/tristanv2/flds/flds.tot.00003
graphet/tests/data/tristanv2/flds/flds.tot.00004
graphet/tests/data/tristanv2/prtl/prtl.tot.00000
graphet/tests/data/tristanv2/prtl/prtl.tot.00001
graphet/tests/data/tristanv2/prtl/prtl.tot.00002
graphet/tests/data/tristanv2/prtl/prtl.tot.00003
graphet/tests/data/tristanv2/prtl/prtl.tot.00004
graphet/tests/data/tristanv2/spec/spec.tot.00000
graphet/tests/data/tristanv2/spec/spec.tot.00001
graphet/tests/data/tristanv2/spec/spec.tot.00002
graphet/tests/data/tristanv2/spec/spec.tot.00003
graphet/tests/data/tristanv2/spec/spec.tot.00004
graphet/utils/__init__.py
graphet/utils/fmt.py
graphet/utils/typing.py
graph_et-0.1.4.dist-info/METADATA
graph_et-0.1.4.dist-info/WHEEL
graph_et-0.1.4.dist-info/licenses/LICENSE
graph_et-0.1.4.dist-info/RECORD
