Metadata-Version: 2.4
Name: graph-et
Version: 0.1.4
Summary: library for efficient loading of particle-in-cell simulation data produced by a variety of different codes
Project-URL: Repository, https://github.com/haykh/graph-et
Author-email: Hayk <haykh.astro@gmail.com>
Maintainer-email: Hayk <haykh.astro@gmail.com>
License: BSD 3-Clause License
License-File: LICENSE
Classifier: Development Status :: 5 - Production/Stable
Classifier: Intended Audience :: Education
Classifier: Intended Audience :: Science/Research
Classifier: License :: OSI Approved :: BSD License
Classifier: Programming Language :: Python :: 3 :: Only
Classifier: Programming Language :: Python :: 3.8
Classifier: Programming Language :: Python :: 3.9
Classifier: Programming Language :: Python :: 3.10
Classifier: Programming Language :: Python :: 3.11
Classifier: Programming Language :: Python :: 3.12
Requires-Python: >=3.8
Requires-Dist: bokeh>=3.1.0
Requires-Dist: dask[distributed]>=2024.1.1
Requires-Dist: h5pickle>=0.4.2
Requires-Dist: h5py>=3.10.0
Requires-Dist: numpy>=1.26.4
Requires-Dist: pandas>=2.2.0
Requires-Dist: pyarrow>=15.0.0
Requires-Dist: xarray>=2024.1.1
